{
  "name": "University Ecosystem",
  "dockerComposeFile": ["../docker-compose.yml"],
  "service": "backend",
  "workspaceFolder": "/workspace",
  "shutdownAction": "stopCompose",
  "postCreateCommand": "pip install --no-cache-dir -r root/requirements.txt && npm install --prefix root/frontend",
  "customizations": {
    "vscode": {
      "extensions": [
        "ms-python.python",
        "ms-python.vscode-pylance",
        "ms-azuretools.vscode-docker",
        "esbenp.prettier-vscode",
        "dbaeumer.vscode-eslint"
      ],
      "settings": {
        "python.analysis.typeCheckingMode": "basic",
        "python.defaultInterpreterPath": "/usr/local/bin/python"
      }
    }
  },
  "forwardPorts": [8000, 5173],
  "remoteUser": "vscode"
}
